tonb/__init__.py
tonb/api.py
tonb-1.0.0.dist-info/METADATA
tonb-1.0.0.dist-info/WHEEL
tonb-1.0.0.dist-info/licenses/LICENSE
tonb-1.0.0.dist-info/RECORD
