Metadata-Version: 2.1
Name: tonb
Version: 1.0.0
Summary: TONB Merchant Backend API Python Client Library
Project-URL: Homepage, https://gitlab.tonb.io/tonb/python-merchant-api-client
Project-URL: Bug Tracker, https://gitlab.tonb.io/tonb/python-merchant-api-client/issues
License-File: LICENSE
Classifier: License :: OSI Approved :: MIT License
Classifier: Operating System :: OS Independent
Classifier: Programming Language :: Python :: 3
Requires-Python: >=3.7
